personalities/__init__.py
personalities/ada_lovelace.md
personalities/personality_loader.py
personalities/ritchie_thompson.md
personalities/zeekay.json
hanzo_persona-1.0.0.dist-info/METADATA
hanzo_persona-1.0.0.dist-info/WHEEL
hanzo_persona-1.0.0.dist-info/top_level.txt
hanzo_persona-1.0.0.dist-info/RECORD
