Metadata-Version: 2.4
Name: hanzo-persona
Version: 1.0.0
Summary: Unified programmer personality profiles for Hanzo ecosystem
Author: Hanzo AI
License: MIT
Project-URL: Homepage, https://github.com/hanzoai/persona
Project-URL: Repository, https://github.com/hanzoai/persona.git
Keywords: hanzo,personality,personas,programmer,ai
Requires-Python: >=3.8
